scoary/KeyValueStore.py
scoary/ScoaryTree.py
scoary/__init__.py
scoary/analyze_trait.py
scoary/final_overview.py
scoary/init_multiprocessing.py
scoary/load_genes.py
scoary/load_traits.py
scoary/newick.py
scoary/permutations.py
scoary/picking.py
scoary/progressbar.py
scoary/scoary.py
scoary/scoary_1_picking.py
scoary/upgma.py
scoary/utils.py
scoary/vcf2scoary.py
scoary_2-0.0.15.dist-info/METADATA
scoary_2-0.0.15.dist-info/WHEEL
scoary_2-0.0.15.dist-info/entry_points.txt
scoary_2-0.0.15.dist-info/RECORD
